motodenik-0.1.0.dist-info/METADATA
motodenik-0.1.0.dist-info/WHEEL
motodenik/__init__.py
motodenik/journal.py
motodenik-0.1.0.dist-info/RECORD
