Metadata-Version: 2.1
Name: motodenik
Version: 0.1.0
Summary: Demo projekt pro pytest kurz.
Author-Email: Jan Kolomaznik <jan.kolomaznik@gmail.com>
License: MIT
Requires-Python: >=3.11
